guipyter/__init__.py
guipyter/__version__
guipyter/jtkinter/__init__.py
guipyter/jtkinter/base.py
guipyter/jtkinter/jtkinter.py
guipyter/jtkinter/tools/__init__.py
guipyter/jtkinter/tools/comparison.py
guipyter/notebook_tools/__init__.py
guipyter/notebook_tools/utils.py
guipyter/utils/__init__.py
guipyter/utils/cli_tools.py
guipyter/utils/dataloader.py
guipyter-0.0.14.dist-info/DESCRIPTION.rst
guipyter-0.0.14.dist-info/METADATA
guipyter-0.0.14.dist-info/RECORD
guipyter-0.0.14.dist-info/WHEEL
guipyter-0.0.14.dist-info/metadata.json
guipyter-0.0.14.dist-info/top_level.txt
