Metadata-Version: 2.0
Name: guipyter
Version: 0.0.14
Summary: GUI tools for jupyter notebook.
Home-page: https://github.com/draperjames/guipyter
Author: James Draper
Author-email: james.draper@duke.edu
License: MIT
Keywords: Jupyter Notebook
Platform: UNKNOWN
Classifier: Development Status :: 3 - Alpha
Classifier: Intended Audience :: Developers
Classifier: Topic :: Software Development :: Build Tools
Classifier: License :: OSI Approved :: MIT License
Classifier: Programming Language :: Python :: 3.4
Classifier: Programming Language :: Python :: 3.5
Classifier: Programming Language :: Python :: 3.6
Requires-Dist: pandas
Requires-Dist: xlrd
